FSM_Baseball.v
`timescale 1ns/1ns

module FSM_Baseball(pitch, rstn, clk, result);
    input [1:0] pitch;// 00: none, 01: strike, 10: ball
    input rstn, clk;
    output [1:0] result;// 00: none, 01: strike_out, 10: four_ball

    wire [1:0] pitch;
    wire rstn, clk;
    reg [1:0] result;
    reg [4:0] s_state;
    reg [4:0] s_next_state;
    reg [4:0] b_state;
    reg [4:0] b_next_state;

    localparam [2:0] s0 = 3'b000, s1 = 3'b001, s2 = 3'b010,
                     b0 = 3'b011, b1 = 3'b100, b2 = 3'b101, b3 = 3'b110,
                     out = 3'b111;


    always@(posedge clk or rstn) begin
        if (rstn == 1'b0) begin
            s_state = s0;
            b_state = b0;
            s_next_state = s0;
            b_next_state = b0;
            result = 2'b00;
        end else begin
            if (pitch == 2'b01) begin
                case(s_next_state)
                    s0: begin
                        s_next_state <= s1;
                        s_state <= s_next_state;
                    end
                    s1: begin
                        s_next_state <= s2;
                        s_state <= s_next_state;
                    end
                    s2: begin
                        s_next_state <= out;
                        s_state <= s_next_state;
                    end
                    out : begin
                        s_next_state <= s0;
                        s_state <= s_next_state;
                        b_next_state <= b0;
                        b_state <= b_next_state;
                    end
                endcase
            end else if (pitch == 2'b10) begin
                case(b_next_state)
                    b0: begin
                        b_next_state <= b1;
                        b_state <= b_next_state;
                    end
                    b1: begin
                        b_next_state <= b2;
                        b_state <= b_next_state;
                    end
                    b2: begin
                        b_next_state <= b3;
                        b_state <= b_next_state;
                    end
                    b3: begin
                        b_next_state <= out;
                        b_state <= b_next_state;
                    end
                    out : begin
                        s_next_state <= s0;
                        s_state <= s_next_state;
                        b_next_state <= b0;
                        b_state <= b_next_state;
                    end
                endcase
            end 
            else if (pitch == 2'b00) begin
                s_next_state <= s0;
                s_state <= s_next_state;
                b_next_state <= b0;
                b_state <= b_next_state;
            end
        end
    end

    always @(s_state) begin
        case (s_state)
            s0: result <= 2'b00;
            s1: result <= 2'b00;
            s2: result <= 2'b00;
            out: result <= 2'b01;
        endcase
    end

    always @(b_state) begin
        case (b_state)
            b0: result <= 2'b00;
            b1: result <= 2'b00;
            b2: result <= 2'b00;
            b3: result <= 2'b00;
            out: result <= 2'b10;
        endcase
    end

endmodule

FSM_Baseball_tb.v
`timescale 1ns/1ns
`include "FSM_Baseball.v"

module FSM_Baseball_TEST;
    reg [1:0] pitch;
    reg rstn, clk;
    wire [1:0] result;

    FSM_Baseball u_FSM_Baseball(.pitch(pitch), .rstn(rstn), .clk(clk), .result(result));

    always #5 clk = ~clk;

    initial begin
        $dumpfile("FSM_Baseball.vcd");
        $dumpvars(0);
    end

    initial begin
        rstn = 1'b0; pitch = 2'b00; clk = 1'b0;
        #10 rstn = 1'b1;
        #10 pitch = 2'b01;//s
        #10 pitch = 2'b01;//s
        #10 pitch = 2'b01;//s - out
        #10 pitch = 2'b00;
        #10 pitch = 2'b00;
        #10 pitch = 2'b10;//b
        #10 pitch = 2'b10;//b
        #10 pitch = 2'b10;//b
        #10 pitch = 2'b10;//b - four_ball
        #10 pitch = 2'b00;
        #10 pitch = 2'b00;
        #10 pitch = 2'b10;//b
        #10 pitch = 2'b10;//b
        #10 pitch = 2'b01;//s
        #10 pitch = 2'b10;//b
        #10 pitch = 2'b01;//s
        #10 pitch = 2'b10;//b - four_ball
        #10 pitch = 2'b00;
        #10 pitch = 2'b00;
        #10 $finish;
    end

endmodule

FSM_Baseball.vcd
$date
	Sun May 31 22:47:46 2026
$end
$version
	Icarus Verilog
$end
$timescale
	1ns
$end
$scope module FSM_Baseball_TEST $end
$var wire 2 ! result [1:0] $end
$var reg 1 " clk $end
$var reg 2 # pitch [1:0] $end
$var reg 1 $ rstn $end
$scope module u_FSM_Baseball $end
$var wire 1 " clk $end
$var wire 2 % pitch [1:0] $end
$var wire 1 $ rstn $end
$var parameter 3 & b0 $end
$var parameter 3 ' b1 $end
$var parameter 3 ( b2 $end
$var parameter 3 ) b3 $end
$var parameter 3 * out $end
$var parameter 3 + s0 $end
$var parameter 3 , s1 $end
$var parameter 3 - s2 $end
$var reg 5 . b_next_state [4:0] $end
$var reg 5 / b_state [4:0] $end
$var reg 2 0 result [1:0] $end
$var reg 5 1 s_next_state [4:0] $end
$var reg 5 2 s_state [4:0] $end
$upscope $end
$upscope $end
$enddefinitions $end
$comment Show the parameter values. $end
$dumpall
b10 -
b1 ,
b0 +
b111 *
b110 )
b101 (
b100 '
b11 &
$end
#0
$dumpvars
b0 2
b0 1
b0 0
b11 /
b11 .
b0 %
0$
b0 #
0"
b0 !
$end
#5
1"
#10
0"
1$
#15
1"
#20
0"
b1 #
b1 %
#25
b1 1
1"
#30
0"
#35
b1 2
b10 1
1"
#40
0"
#45
b10 2
b111 1
1"
#50
0"
b0 #
b0 %
#55
b1 !
b1 0
b111 2
b0 1
1"
#60
0"
#65
b0 !
b0 0
b0 2
1"
#70
0"
b10 #
b10 %
#75
b100 .
1"
#80
0"
#85
b100 /
b101 .
1"
#90
0"
#95
b101 /
b110 .
1"
#100
0"
#105
b110 /
b111 .
1"
#110
0"
b0 #
b0 %
#115
b10 !
b10 0
b111 /
b11 .
1"
#120
0"
#125
b0 !
b0 0
b11 /
1"
#130
0"
b10 #
b10 %
#135
b100 .
1"
#140
0"
#145
b100 /
b101 .
1"
#150
0"
b1 #
b1 %
#155
b1 1
1"
#160
0"
b10 #
b10 %
#165
b101 /
b110 .
1"
#170
0"
b1 #
b1 %
#175
b1 2
b10 1
1"
#180
0"
b10 #
b10 %
#185
b110 /
b111 .
1"
#190
0"
b0 #
b0 %
#195
b10 !
b10 0
b111 /
b11 .
b10 2
b0 1
1"
#200
0"
#205
b0 !
b0 0
b11 /
b0 2
1"
